{
    "AX": {
        "error": 0.009863612069159106,
        "error_type": "SEM",
        "filter_outliers_dict": {
            "filter_outliers": true,
            "iterations": 1,
            "std_devs": 3
        },
        "fit": "average",
        "value": 0.23627529580063467
    },
    "CDD": {
        "error": 0.0,
        "error_type": "SEM",
        "filter_outliers_dict": {
            "filter_outliers": true,
            "iterations": 1,
            "std_devs": 10
        },
        "fit": "average",
        "value": 0.0
    },
    "H1": {
        "error": 0.008317917410229827,
        "error_type": "SEM",
        "filter_outliers_dict": {
            "filter_outliers": true,
            "iterations": 1,
            "std_devs": 3
        },
        "fit": "average",
        "value": 0.03477293329384446
    },
    "H2": {
        "error": 0.06507791077213598,
        "error_type": "SEM",
        "filter_outliers_dict": {
            "filter_outliers": true,
            "iterations": 1,
            "std_devs": 3
        },
        "fit": "average",
        "value": -0.32612169791967227
    },
    "L1": {
        "error": 0.0039497931717783555,
        "error_type": "SEM",
        "filter_outliers_dict": {
            "filter_outliers": true,
            "iterations": 1,
            "std_devs": 3
        },
        "fit": "average",
        "value": 0.04246505449510748
    },
    "L2": {
        "error": 0.005012640858721388,
        "error_type": "SEM",
        "filter_outliers_dict": {
            "filter_outliers": true,
            "iterations": 1,
            "std_devs": 3
        },
        "fit": "average",
        "value": -0.050039430051226415
    }
}