{
    "Ar36": {
        "error": 0.00016533642065525938,
        "error_type": "SEM",
        "filter_outliers_dict": {
            "filter_outliers": true,
            "iterations": 1,
            "std_devs": 2
        },
        "fit": "linear",
        "value": 0.005788362179570872
    },
    "Ar37": {
        "error": 0.004275504747062713,
        "error_type": "SEM",
        "filter_outliers_dict": {
            "filter_outliers": true,
            "iterations": 1,
            "std_devs": 2
        },
        "fit": "linear",
        "value": -0.009279962957060439
    },
    "Ar38": {
        "error": 0.004133586744563583,
        "error_type": "SEM",
        "filter_outliers_dict": {
            "filter_outliers": true,
            "iterations": 1,
            "std_devs": 2
        },
        "fit": "linear",
        "value": 0.03448728288503388
    },
    "Ar39": {
        "error": 0.015234493406978307,
        "error_type": "SEM",
        "filter_outliers_dict": {
            "filter_outliers": true,
            "iterations": 1,
            "std_devs": 2
        },
        "fit": "Parabolic",
        "value": -0.0339881027188834
    },
    "Ar40": {
        "error": 0.015682124303445323,
        "error_type": "SEM",
        "filter_outliers_dict": {
            "filter_outliers": true,
            "iterations": 1,
            "std_devs": 3
        },
        "fit": "Parabolic",
        "value": 0.16833630964481744
    },
    "Ar41": {
        "error": 0.021894942874376516,
        "error_type": "SEM",
        "filter_outliers_dict": {
            "filter_outliers": true,
            "iterations": 1,
            "std_devs": 3
        },
        "fit": "average",
        "value": -0.2010926234261759
    }
}